ffmpeg_mcp_lite/__init__.py
ffmpeg_mcp_lite/__main__.py
ffmpeg_mcp_lite/config.py
ffmpeg_mcp_lite/server.py
ffmpeg_mcp_lite/tools/__init__.py
ffmpeg_mcp_lite/tools/audio.py
ffmpeg_mcp_lite/tools/compress.py
ffmpeg_mcp_lite/tools/convert.py
ffmpeg_mcp_lite/tools/frames.py
ffmpeg_mcp_lite/tools/info.py
ffmpeg_mcp_lite/tools/merge.py
ffmpeg_mcp_lite/tools/subtitles.py
ffmpeg_mcp_lite/tools/trim.py
ffmpeg_mcp_lite-0.2.1.dist-info/METADATA
ffmpeg_mcp_lite-0.2.1.dist-info/WHEEL
ffmpeg_mcp_lite-0.2.1.dist-info/entry_points.txt
ffmpeg_mcp_lite-0.2.1.dist-info/licenses/LICENSE
ffmpeg_mcp_lite-0.2.1.dist-info/RECORD
