Metadata-Version: 2.4
Name: ffmpeg-mcp-lite
Version: 0.2.1
Summary: MCP server providing video and audio processing capabilities through FFmpeg
Project-URL: Homepage, https://github.com/kevinwatt/ffmpeg-mcp-lite
Project-URL: Repository, https://github.com/kevinwatt/ffmpeg-mcp-lite
Project-URL: Issues, https://github.com/kevinwatt/ffmpeg-mcp-lite/issues
Author-email: Kevin Watt <kevin@watt.tw>
License: MIT
License-File: LICENSE
Keywords: ai,audio,claude,ffmpeg,mcp,model-context-protocol,video
Classifier: Development Status :: 4 - Beta
Classifier: Intended Audience :: Developers
Classifier: License :: OSI Approved :: MIT License
Classifier: Programming Language :: Python :: 3
Classifier: Programming Language :: Python :: 3.10
Classifier: Programming Language :: Python :: 3.11
Classifier: Programming Language :: Python :: 3.12
Classifier: Topic :: Multimedia :: Sound/Audio
Classifier: Topic :: Multimedia :: Video
Requires-Python: >=3.10
Requires-Dist: mcp>=1.0.0
